iii_tap_pendo/__init__.py
iii_tap_pendo/discover.py
iii_tap_pendo/schemas/accounts.json
iii_tap_pendo/schemas/events.json
iii_tap_pendo/schemas/feature_events.json
iii_tap_pendo/schemas/features.json
iii_tap_pendo/schemas/guide_events.json
iii_tap_pendo/schemas/guides.json
iii_tap_pendo/schemas/metadata_accounts.json
iii_tap_pendo/schemas/metadata_visitors.json
iii_tap_pendo/schemas/page_events.json
iii_tap_pendo/schemas/pages.json
iii_tap_pendo/schemas/poll_events.json
iii_tap_pendo/schemas/shared/metadata.json
iii_tap_pendo/schemas/track_events.json
iii_tap_pendo/schemas/track_types.json
iii_tap_pendo/schemas/visitor_history.json
iii_tap_pendo/schemas/visitors.json
iii_tap_pendo/streams.py
iii_tap_pendo/sync.py
iii_tap_pendo/utils.py
iii_tap_pendo-0.4.3.dist-info/LICENSE
iii_tap_pendo-0.4.3.dist-info/WHEEL
iii_tap_pendo-0.4.3.dist-info/METADATA
iii_tap_pendo-0.4.3.dist-info/RECORD
