Metadata-Version: 2.1
Name: iii-tap-pendo
Version: 0.4.3
Summary: Singer.io tap for extracting data from Pendo. Forked from https://github.com/singer-io/tap-pendo
Author: Everet Rummel
Author-email: everet.rummel@clarivate.com
Requires-Python: >=3.7,<4.0
Classifier: Programming Language :: Python :: 3
Classifier: Programming Language :: Python :: 3.7
Classifier: Programming Language :: Python :: 3.8
Classifier: Programming Language :: Python :: 3.9
Classifier: Programming Language :: Python :: 3.10
Requires-Dist: backoff (==1.8.0)
Requires-Dist: ijson (==3.1.4)
Requires-Dist: pyhumps (==1.3.1)
Requires-Dist: requests (>=2.28.1,<3.0.0)
Requires-Dist: singer-python (==5.12.2)
